easemlschema/__init__.py
easemlschema/dataset.py
easemlschema/schema.py
test/__init__.py
test/test_dataset_generate.py
test/test_dataset_infer.py
test/test_schema_match.py
test/test_schema_validate.py
easemlschema-0.1.13.dist-info/LICENCE
easemlschema-0.1.13.dist-info/METADATA
easemlschema-0.1.13.dist-info/WHEEL
easemlschema-0.1.13.dist-info/top_level.txt
easemlschema-0.1.13.dist-info/RECORD
